pyvault/__init__.py
pyvault/command_line.py
pyvault20-0.1.23.dist-info/LICENSE
pyvault20-0.1.23.dist-info/METADATA
pyvault20-0.1.23.dist-info/WHEEL
pyvault20-0.1.23.dist-info/entry_points.txt
pyvault20-0.1.23.dist-info/top_level.txt
pyvault20-0.1.23.dist-info/RECORD
