Metadata-Version: 2.1
Name: pyvault20
Version: 0.1.23
Summary: Vault encryption tool.
Home-page: https://github.com/thecodeforge/pyvault
Requires-Python: >=3.11
License-File: LICENSE
Requires-Dist: pychacha
Requires-Dist: pyyaml
Requires-Dist: requests
Requires-Dist: rsa
